[
    {
        "id":1,
        "firstName":"Eman",
        "lastName":"Salah",
        "email":"eman@gmail.com",
        "userName":"eman1",
        "password":"123"
    },
    {
        "id":1,
        "firstName":"Eman",
        "lastName":"Salah2",
        "email":"eman@gmail.com",
        "userName":"eman2",
        "password":"123"
    },
    {
        "id":1,
        "firstName":"Eman",
        "lastName":"Salah3",
        "email":"eman@gmail.com",
        "userName":"eman3",
        "password":"123"
    },
    {
        "id":1,
        "firstName":"Eman",
        "lastName":"Salah4",
        "email":"eman@gmail.com",
        "userName":"eman4",
        "password":"123"
    },
    {
        "id":1,
        "firstName":"Eman",
        "lastName":"Salah5",
        "email":"eman@gmail.com",
        "userName":"eman5",
        "password":"123"
    }
]